Metadata-Version: 2.1
Name: django-reports-admin
Version: 1.1.0
Summary: A Django Admin add-on which adds functionality to export data in customized forms of output.
Home-page: https://github.com/gadventures/django-reports-admin
Author: G Adventures
Author-email: software@gadventures.com
License: MIT
Keywords: django reports admin
Platform: UNKNOWN
Classifier: Intended Audience :: Developers
Classifier: License :: OSI Approved :: MIT License
Classifier: Natural Language :: English
Classifier: Programming Language :: Python :: 3.5
Classifier: Programming Language :: Python :: 3.6
